Metadata-Version: 2.1
Name: grpcio-fips
Version: 1.70.0
Summary: HTTP/2-based RPC framework
Home-page: https://grpc.io
Author: The gRPC Authors
Author-email: grpc-io@googlegroups.com
License: Apache License 2.0
Project-URL: Source Code, https://github.com/grpc/grpc
Project-URL: Bug Tracker, https://github.com/grpc/grpc/issues
Project-URL: Documentation, https://grpc.github.io/grpc/python
Platform: UNKNOWN
Classifier: Development Status :: 5 - Production/Stable
Classifier: Programming Language :: Python
Classifier: Programming Language :: Python :: 3
Classifier: Programming Language :: Python :: 3.8
Classifier: Programming Language :: Python :: 3.9
Classifier: Programming Language :: Python :: 3.10
Classifier: Programming Language :: Python :: 3.11
Classifier: Programming Language :: Python :: 3.12
Classifier: Programming Language :: Python :: 3.13
Classifier: License :: OSI Approved :: Apache Software License
Requires-Python: >=3.8
Provides-Extra: protobuf
Requires-Dist: grpcio-tools>=1.70.0; extra == "protobuf"
